disgrasya/__init__.py
disgrasya/generate.py
disgrasya/main.py
disgrasya/ccn/__init__.py
disgrasya/ccn/cybersource2.py
disgrasya/ccn/ppcp.py
disgrasya/cvv/__init__.py
disgrasya/cvv/cybersource1.py
disgrasya/cvv/nmi.py
disgrasya/cvv/paypal_pro_payflow.py
disgrasya/cvv/paypalpro.py
disgrasya/cvv/stripe_cc.py
disgrasya/testing/__init__.py
disgrasya/testing/lookup.py
disgrasya/woocommmerce/__init__.py
disgrasya/woocommmerce/domaintoip.py
disgrasya/woocommmerce/ipranger.py
disgrasya/woocommmerce/ipschecker.py
disgrasya/woocommmerce/revereseip.py
disgrasya/woocommmerce/woocommercepm.py
disgrasya-11.40.0.dist-info/METADATA
disgrasya-11.40.0.dist-info/WHEEL
disgrasya-11.40.0.dist-info/entry_points.txt
disgrasya-11.40.0.dist-info/top_level.txt
disgrasya-11.40.0.dist-info/RECORD
